{"id": "on-television-advertising", "title": "On Television Advertising", "content": "Quite literally... on advertising TVs. Don\u2019t you ever wonder what goes through a marketer's mind when they have to develop a television advert for a TV.<div class=\"readmore\"> Their training will force them to look at the desirable aspects of the TV \u2013 the most important being image clarity. The general advertising technique used is to show this aspect to the viewers on TV.  Is it possible that they realised that the only people who will see the true clarity of the image are those who already have better TVs.</div>", "published": "2010-01-03T13:20:00.004000+02:00", "updated": "2011-05-26T17:03:54.412000+02:00", "draft": false, "categories": ["technology", "incompetence", "advertising"]}